<?xml version="1.0" encoding="UTF-8"?>
<activity id="51406" moduleid="575793" modulename="label" contextid="2592356">
  <label id="51406">
    <name>Questionário auxiliar sobre Expressões algébricas ...</name>
    <intro>&lt;p dir="ltr" style="text-align: left;"&gt;Questionário auxiliar sobre Expressões algébricas 1:&amp;nbsp;Introdução às expressões algébricas. Expressões algébricas polinomiais.&lt;/p&gt;</intro>
    <introformat>1</introformat>
    <timemodified>1681245111</timemodified>
  </label>
</activity>